pytest_jira_xray-0.9.3.dist-info/licenses/LICENSE
pytest_xray/__init__.py
pytest_xray/constant.py
pytest_xray/evidence.py
pytest_xray/exceptions.py
pytest_xray/file_publisher.py
pytest_xray/helper.py
pytest_xray/hooks.py
pytest_xray/plugin.py
pytest_xray/xray_plugin.py
pytest_xray/xray_publisher.py
pytest_jira_xray-0.9.3.dist-info/METADATA
pytest_jira_xray-0.9.3.dist-info/WHEEL
pytest_jira_xray-0.9.3.dist-info/entry_points.txt
pytest_jira_xray-0.9.3.dist-info/top_level.txt
pytest_jira_xray-0.9.3.dist-info/RECORD
