Metadata-Version: 2.4
Name: pytest-jira-xray
Version: 0.9.3
Summary: pytest plugin to integrate tests with JIRA XRAY
Author-email: Lukasz Fundakowski <fundakol@yahoo.com>
License-Expression: Apache-2.0
Project-URL: homepage, https://github.com/fundakol/pytest-jira-xray
Keywords: pytest, JIRA, XRAY
Classifier: Development Status :: 4 - Beta
Classifier: Programming Language :: Python :: 3
Classifier: Programming Language :: Python :: 3.9
Classifier: Programming Language :: Python :: 3.10
Classifier: Programming Language :: Python :: 3.11
Classifier: Programming Language :: Python :: 3.12
Classifier: Programming Language :: Python :: 3.13
Classifier: Operating System :: OS Independent
Classifier: Framework :: Pytest
Requires-Python: >=3.9
License-File: LICENSE
Requires-Dist: pytest>=6.2.4
Requires-Dist: requests>=2.27.0
Dynamic: license-file
